setup.py
tests/__init__.py
tests/tags_extractor.py
tests/twitter_urls.py
urlsresolver/__init__.py
urlsresolver/__main__.py
urlsresolver/__version.py
urlsresolver.egg-info/PKG-INFO
urlsresolver.egg-info/SOURCES.txt
urlsresolver.egg-info/dependency_links.txt
urlsresolver.egg-info/pbr.json
urlsresolver.egg-info/requires.txt
urlsresolver.egg-info/top_level.txt