Metadata-Version: 1.1
Name: urlsresolver
Version: 1.2.0
Summary: Python urls resolver library
Home-page: https://github.com/phpdude/python-urlsresolver
Author: Alexandr I. Shurigin
Author-email: ya@helldude.ru
License: UNKNOWN
Platform: UNKNOWN
Classifier: Development Status :: 4 - Beta
Classifier: Intended Audience :: Developers
Classifier: License :: OSI Approved :: GNU General Public License v3 or later (GPLv3+)
Classifier: Natural Language :: English
Classifier: Operating System :: OS Independent
Classifier: Programming Language :: Python
Classifier: Topic :: Internet :: WWW/HTTP
Classifier: Topic :: Software Development :: Libraries :: Python Modules
Classifier: Topic :: System :: Networking
Classifier: Topic :: Utilities
